{
  "name": "body-kindness-transform-your-health-from-the-inside-out-and-never-diet-again",
  "version": "1.0.0",
  "description": "Rebecca Scritchfield's science-based, compassionate approach to health — replacing dieting, food rules, and body criticism with intuitive eating, joyful movement, and self-love.",
  "publisher": "heardlyapp",
  "license": "MIT",
  "homepage": "https://clawhub.ai/heardlyapp/body-kindness-transform-your-health-from-the-inside-out-and-never-diet-again",
  "useCase": "Develop a healthier relationship with food, exercise, sleep, emotions, and your body through the Body Kindness philosophy of love, connection, and care.",
  "knownRisks": [
    "May challenge deeply held beliefs about dieting and weight",
    "Not suitable for those seeking rapid weight loss",
    "May trigger discomfort around food and body issues"
  ],
  "tags": ["health", "wellness", "intuitive-eating", "body-image", "self-compassion", "nutrition", "fitness", "mental-health", "self-care", "body-acceptance"],
  "openclaw": {
    "emoji": "🫶",
    "category": "health"
  }
}
